fpr/__init__.py
fpr/graph_util.py
fpr/quiz_util.py
fpr/run_pipeline.py
fpr/rx_util.py
fpr/serialize_util.py
fpr/clients/__init__.py
fpr/clients/cratesio.py
fpr/clients/npm_registry.py
fpr/clients/npmsio.py
fpr/db/__init__.py
fpr/db/connect.py
fpr/db/schema.py
fpr/docker/__init__.py
fpr/docker/client.py
fpr/docker/containers.py
fpr/docker/images.py
fpr/docker/log_reader.py
fpr/docker/volumes.py
fpr/models/__init__.py
fpr/models/docker_image.py
fpr/models/git_ref.py
fpr/models/github.py
fpr/models/language.py
fpr/models/nodejs.py
fpr/models/org_repo.py
fpr/models/package_meta_result.py
fpr/models/pipeline.py
fpr/models/rust.py
fpr/pipelines/__init__.py
fpr/pipelines/crate_graph.py
fpr/pipelines/dep_graph.py
fpr/pipelines/fetch_package_data.py
fpr/pipelines/find_dep_files.py
fpr/pipelines/find_git_refs.py
fpr/pipelines/github_metadata.py
fpr/pipelines/postprocess.py
fpr/pipelines/run_repo_tasks.py
fpr/pipelines/rust_changelog.py
fpr/pipelines/save_to_db.py
fpr/pipelines/util.py
dependency_observatory_scanner-2020.3.24.dist-info/LICENSE
dependency_observatory_scanner-2020.3.24.dist-info/METADATA
dependency_observatory_scanner-2020.3.24.dist-info/WHEEL
dependency_observatory_scanner-2020.3.24.dist-info/top_level.txt
dependency_observatory_scanner-2020.3.24.dist-info/zip-safe
dependency_observatory_scanner-2020.3.24.dist-info/RECORD
