Metadata-Version: 2.1
Name: dependency-observatory-scanner
Version: 2020.3.24
Summary: Dependency Observatory Scanner: a scanner for software packages and dependencies
Home-page: https://github.com/mozilla-services/dependency-observatory-scanner
Author: Greg Guthe
Author-email: foxsec+dependencyscan@mozilla.com
License: UNKNOWN
Platform: UNKNOWN
Classifier: Development Status :: 4 - Beta
Classifier: Intended Audience :: Developers
Classifier: Intended Audience :: System Administrators
Classifier: License :: OSI Approved :: Mozilla Public License 2.0 (MPL 2.0)
Classifier: Natural Language :: English
Classifier: Programming Language :: Python :: 3 :: Only
Classifier: Topic :: Security
Classifier: Topic :: Software Development :: Quality Assurance
Requires-Python: >=3.8
